[{"word": "contingent workers", "ipa": "", "pos": "", "translations": {"hu": {"definitions": [{"text": "esetleges munkások", "quality": 3}]}}, "source": "english-contracts", "expression_of": "contingent"}, {"word": "contractor", "ipa": "", "pos": "", "translations": {"hu": {"definitions": [{"text": "LoopTroops", "quality": 3}]}}, "source": "english-contracts"}, {"word": "Contractor represents and warrants", "ipa": "", "pos": "", "translations": {"hu": {"definitions": [{"text": "A vállalkozó képviseli és szavatolja:", "quality": 3}]}}, "source": "english-contracts", "expression_of": "contractor"}, {"word": "contractor’s consultant", "ipa": "", "pos": "", "translations": {"hu": {"definitions": [{"text": "Gábor Monostori", "quality": 3}]}}, "source": "english-contracts", "expression_of": "contractor’s"}]